MANIFEST.in
README.rst
setup.py
diafo/__init__.py
diafo/admin.py
diafo/apps.py
diafo/form_dynamic.py
diafo/forms.py
diafo/models.py
diafo/tests.py
diafo/urls.py
diafo/views.py
diafo.egg-info/PKG-INFO
diafo.egg-info/SOURCES.txt
diafo.egg-info/dependency_links.txt
diafo.egg-info/top_level.txt
diafo/migrations/0001_initial.py
diafo/migrations/0002_auto_20171126_1127.py
diafo/migrations/0003_auto_20171126_1155.py
diafo/migrations/0004_auto_20171126_1204.py
diafo/migrations/0005_auto_20171126_1204.py
diafo/migrations/0006_auto_20171126_1209.py
diafo/migrations/0007_auto_20171126_1314.py
diafo/migrations/0008_auto_20171126_1334.py
diafo/migrations/__init__.py
diafo/static/diafo/css/style.css
diafo/static/diafo/fonts/Exo2-Regular.ttf
diafo/static/diafo/fonts/Heebo-Regular.ttf
diafo/static/diafo/images/4.jpeg
diafo/static/diafo/images/4.jpg
diafo/static/diafo/images/Thumbs.db
diafo/static/diafo/images/ty.jpg
diafo/templates/diafo/add_ques.html
diafo/templates/diafo/admin_view.html
diafo/templates/diafo/base.html
diafo/templates/diafo/edit_ques.html
diafo/templates/diafo/info.html
diafo/templates/diafo/user_view.html
diafo/templates/diafo/view_filled_form.html